htuneml
