Metadata-Version: 2.1
Name: htuneml
Version: 0.0.6
Summary: Monitor machine learning experiments
Home-page: http://github.com/johnsmithm/htuneml
Author: Ion Mosnoi
Author-email: moshnoi2000@gmail.com
License: MIT
Platform: UNKNOWN
